pyhtmlconv/__init__.py
pyhtmlconv/compat.py
pyhtmlconv/converter.py
pyhtmlconv/img.py
pyhtmlconv/pdf.py
pyhtmlconv/tools.py
pyhtmlconv-1.3.dist-info/LICENSE
pyhtmlconv-1.3.dist-info/METADATA
pyhtmlconv-1.3.dist-info/WHEEL
pyhtmlconv-1.3.dist-info/top_level.txt
pyhtmlconv-1.3.dist-info/RECORD
